zappanel/__init__.py
zappanel-0.0.1.dist-info/licenses/LICENSE
zappanel-0.0.1.dist-info/METADATA
zappanel-0.0.1.dist-info/WHEEL
zappanel-0.0.1.dist-info/top_level.txt
zappanel-0.0.1.dist-info/RECORD
