Metadata-Version: 2.4
Name: zappanel
Version: 0.0.1
Summary: Fast-install admin panel supporting FastAPI, Flask, and SQLAlchemy
Author-email: Shahin <nuoqte@gmail.com>
License: MIT
License-File: LICENSE
Requires-Dist: fastapi
Requires-Dist: sqlalchemy
Dynamic: license-file
